{"name":"GET-as user i want to see all categories with invalid url","id":"as-user-i-want-to-see-all-categories-with-invalid-url;get-as-user-i-want-to-see-all-categories-with-invalid-url","testSteps":[{"number":1,"description":"Given I set get api to endpoints","duration":10,"startTime":"2022-05-17T20:33:31.411579900+08:00[Asia/Makassar]","result":"SUCCESS","precondition":false,"level":0,"children":[{"number":2,"description":"I set get api to endpoints","duration":1,"startTime":"2022-05-17T20:33:31.420588300+08:00[Asia/Makassar]","result":"SUCCESS","precondition":false,"level":1}]},{"number":3,"description":"When I send get request HTTP","duration":100,"startTime":"2022-05-17T20:33:31.423338200+08:00[Asia/Makassar]","result":"SUCCESS","precondition":false,"level":0,"children":[{"number":4,"description":"I send get request HTTP","duration":99,"startTime":"2022-05-17T20:33:31.423338200+08:00[Asia/Makassar]","result":"SUCCESS","precondition":false,"level":1,"children":[{"number":5,"description":"I set get api to endpoints","duration":0,"startTime":"2022-05-17T20:33:31.425340+08:00[Asia/Makassar]","result":"SUCCESS","precondition":false,"level":2},{"number":6,"description":"GET https://be-qa.alta.id/api/categories122\r","duration":0,"startTime":"2022-05-17T20:33:31.522836400+08:00[Asia/Makassar]","result":"SUCCESS","restQuery":{"method":"GET","path":"https://be-qa.alta.id/api/categories122\r","content":"\r","contentType":"null","requestHeaders":"Accept\u003d*/*\r","requestCookies":"\r","responseHeaders":"Server: nginx/1.14.2\r\nDate: Tue, 17 May 2022 12:33:31 GMT\r\nContent-Type: text/plain; charset\u003dutf-8\r\nContent-Length: 10\r\nConnection: keep-alive\r","responseCookies":"\r","responseBody":"not found\n","statusCode":404},"precondition":false,"level":2}]}]},{"number":7,"description":"Then I recaive with invalid HTTP responce code 404","duration":3,"startTime":"2022-05-17T20:33:31.524829100+08:00[Asia/Makassar]","result":"SUCCESS","precondition":false,"level":0,"children":[{"number":8,"description":"I recaive with invalid HTTP responce code 404","duration":1,"startTime":"2022-05-17T20:33:31.525830900+08:00[Asia/Makassar]","result":"SUCCESS","precondition":false,"level":1}]},{"number":9,"description":"And I not revaice all categories","duration":1,"startTime":"2022-05-17T20:33:31.528832500+08:00[Asia/Makassar]","result":"SUCCESS","precondition":false,"level":0}],"userStory":{"id":"as-user-i-want-to-see-all-categories-with-invalid-url","storyName":"as user i want to see all categories with invalid url","path":"file:///D:/alta%20folder/final%20project/api%20testing/src/test/resources/api/categories.feature","type":"feature"},"featureTag":{"name":"Api/as user i want to see all categories with invalid url","type":"feature","displayName":"Api/as user i want to see all categories with invalid url"},"title":"GET-as user i want to see all categories with invalid url","description":"","startTime":"2022-05-17T20:33:31.408577200+08:00[Asia/Makassar]","duration":121,"projectKey":"","isManualTestingUpToDate":false,"manual":false,"testSource":"Cucumber","result":"SUCCESS"}